odoo/addons/pos_customer_tree_view_vat/README.rst
odoo/addons/pos_customer_tree_view_vat/__init__.py
odoo/addons/pos_customer_tree_view_vat/__manifest__.py
odoo/addons/pos_customer_tree_view_vat/i18n/pos_customer_tree_view_vat.pot
odoo/addons/pos_customer_tree_view_vat/readme/CONTRIBUTORS.rst
odoo/addons/pos_customer_tree_view_vat/readme/CREDITS.rst
odoo/addons/pos_customer_tree_view_vat/readme/DESCRIPTION.rst
odoo/addons/pos_customer_tree_view_vat/static/description/icon.png
odoo/addons/pos_customer_tree_view_vat/static/description/index.html
odoo/addons/pos_customer_tree_view_vat/static/description/printscreen.png
odoo/addons/pos_customer_tree_view_vat/static/src/xml/pos.xml
odoo14_addon_pos_customer_tree_view_vat-14.0.1.0.1.dist-info/METADATA
odoo14_addon_pos_customer_tree_view_vat-14.0.1.0.1.dist-info/WHEEL
odoo14_addon_pos_customer_tree_view_vat-14.0.1.0.1.dist-info/top_level.txt
odoo14_addon_pos_customer_tree_view_vat-14.0.1.0.1.dist-info/RECORD
